hunterx/__init__.py
hunterx/commands/__init__.py
hunterx/commands/complete_template.py
hunterx/commands/config.py
hunterx/commands/hunterx.py
hunterx/commands/tools.py
hunterx/core/Basic.py
hunterx/core/__init__.py
hunterx/core/data_class/__init__.py
hunterx/core/data_class/data_class.py
hunterx/core/http/__init__.py
hunterx/core/http/_requests.py
hunterx/core/http/make_args.py
hunterx/core/http/request_objects.py
hunterx/core/instancemeta.py
hunterx/core/manager_memory.py
hunterx/core/manager_rabbitmq.py
hunterx/core/manager_redis.py
hunterx/database/Cluster.py
hunterx/database/__init__.py
hunterx/database/mysql_orm.py
hunterx/database/mysql_orm_old.py
hunterx/internet/__init__.py
hunterx/internet/proxys.py
hunterx/internet/request_objects.py
hunterx/items/__init__.py
hunterx/items/baseitem.py
hunterx/middlewares/__init__.py
hunterx/middlewares/middleware.py
hunterx/middlewares/middleware_loader.py
hunterx/middlewares/middleware_manager.py
hunterx/piplines/__init__.py
hunterx/piplines/basepipeline.py
hunterx/piplines/pipeline_loader.py
hunterx/piplines/pipelines_manager.py
hunterx/queue/__init__.py
hunterx/queue/memory_queue.py
hunterx/queue/rabbitmq_queue.py
hunterx/queue/redis_queue.py
hunterx/requirements.txt
hunterx/settings.py
hunterx/spiders/MemorySpider.py
hunterx/spiders/RabbitmqSpider.py
hunterx/spiders/RedisSpider.py
hunterx/spiders/__init__.py
hunterx/templates/project/__init__.py.tmpl
hunterx/templates/project/generator.py.tmpl
hunterx/templates/project/items.py.tmpl
hunterx/templates/project/middlewares.py.tmpl
hunterx/templates/project/pipelines.py.tmpl
hunterx/templates/project/settings.py.tmpl
hunterx/templates/project/spiders/__init__.py.tmpl
hunterx/templates/spiders/memory_spider.tmpl
hunterx/templates/spiders/rabbitmq_spider.tmpl
hunterx/templates/spiders/redis_spider.tmpl
hunterx/test/my_project/__init__.py
hunterx/test/my_project/generator.py
hunterx/test/my_project/items.py
hunterx/test/my_project/middleware.py
hunterx-0.1.2.dist-info/LICENSE
hunterx-0.1.2.dist-info/METADATA
hunterx-0.1.2.dist-info/WHEEL
hunterx-0.1.2.dist-info/entry_points.txt
hunterx-0.1.2.dist-info/RECORD
