Metadata-Version: 2.1
Name: hunterx
Version: 0.1.2
Summary: 高效异步并发爬虫框架
Home-page: https://github.com/YSH0313/Hunter
License: LICENSE
Author: 袁少航
Author-email: ysh17600824539@gmail.com
Requires-Python: >=3.11,<4.0
Classifier: License :: Other/Proprietary License
Classifier: Programming Language :: Python :: 3
Classifier: Programming Language :: Python :: 3.11
Classifier: Programming Language :: Python :: 3.12
Classifier: Programming Language :: Python :: 3.13
Requires-Dist: aio-pika (>=9.5.4,<10.0.0)
Requires-Dist: aiohttp (>=3.11.11,<4.0.0)
Requires-Dist: aiomysql (>=0.2.0,<0.3.0)
Requires-Dist: async-timeout (>=5.0.1,<6.0.0)
Requires-Dist: chardet (>=5.2.0,<6.0.0)
Requires-Dist: click (>=8.1.8,<9.0.0)
Requires-Dist: colorama (>=0.4.6,<0.5.0)
Requires-Dist: curl-cffi (>=0.7.4,<0.8.0)
Requires-Dist: dateparser (>=1.2.0,<2.0.0)
Requires-Dist: dbutils (>=3.1.0,<4.0.0)
Requires-Dist: decorator (>=5.1.1,<6.0.0)
Requires-Dist: demjson3 (>=3.0.6,<4.0.0)
Requires-Dist: dotmap (>=1.3.30,<2.0.0)
Requires-Dist: hiredis (>=3.1.0,<4.0.0)
Requires-Dist: httpx (>=0.28.1,<0.29.0)
Requires-Dist: inquirerpy (>=0.3.4,<0.4.0)
Requires-Dist: jsonpath (>=0.82.2,<0.83.0)
Requires-Dist: parsel (>=1.9.1,<2.0.0)
Requires-Dist: pycryptodome (>=3.21.0,<4.0.0)
Requires-Dist: pyexecjs (>=1.5.1,<2.0.0)
Requires-Dist: pymysql (>=1.1.1,<2.0.0)
Requires-Dist: redis (>=5.2.1,<6.0.0)
Requires-Dist: requests (>=2.32.3,<3.0.0)
Requires-Dist: xlrd (>=2.0.1,<3.0.0)
Project-URL: Repository, https://github.com/YSH0313/Hunter
